agenticaiframework/__init__.py
agenticaiframework/communication.py
agenticaiframework/config.py
agenticaiframework/configurations.py
agenticaiframework/evaluation.py
agenticaiframework/evaluation_base.py
agenticaiframework/exceptions.py
agenticaiframework/framework.py
agenticaiframework/hub.py
agenticaiframework/knowledge.py
agenticaiframework/mcp_tools.py
agenticaiframework/monitoring.py
agenticaiframework/processes.py
agenticaiframework/prompts.py
agenticaiframework/tasks.py
agenticaiframework/workflows.py
agenticaiframework/agents/__init__.py
agenticaiframework/communication/__init__.py
agenticaiframework/communication/agent_channel.py
agenticaiframework/communication/manager.py
agenticaiframework/communication/protocols.py
agenticaiframework/communication/remote_agent.py
agenticaiframework/compliance/__init__.py
agenticaiframework/compliance/audit.py
agenticaiframework/compliance/decorators.py
agenticaiframework/compliance/masking.py
agenticaiframework/compliance/policy.py
agenticaiframework/compliance/types.py
agenticaiframework/context/__init__.py
agenticaiframework/context/compression.py
agenticaiframework/context/index.py
agenticaiframework/context/items.py
agenticaiframework/context/manager.py
agenticaiframework/context/types.py
agenticaiframework/context/window.py
agenticaiframework/conversations/__init__.py
agenticaiframework/conversations/logger.py
agenticaiframework/conversations/manager.py
agenticaiframework/core/__init__.py
agenticaiframework/core/agent.py
agenticaiframework/core/manager.py
agenticaiframework/core/runner.py
agenticaiframework/core/types.py
agenticaiframework/enterprise/__init__.py
agenticaiframework/enterprise/ab_testing.py
agenticaiframework/enterprise/adapters.py
agenticaiframework/enterprise/aggregate.py
agenticaiframework/enterprise/aggregate_root.py
agenticaiframework/enterprise/alert_manager.py
agenticaiframework/enterprise/alerting.py
agenticaiframework/enterprise/analytics_engine.py
agenticaiframework/enterprise/analyzer.py
agenticaiframework-2.0.0.dist-info/licenses/LICENSE
agenticaiframework-2.0.0.dist-info/METADATA
agenticaiframework-2.0.0.dist-info/WHEEL
agenticaiframework-2.0.0.dist-info/top_level.txt
agenticaiframework-2.0.0.dist-info/RECORD
