Metadata-Version: 2.4
Name: agenticaiframework
Version: 2.0.0
Summary: AgenticAI - A Python SDK for building agentic applications with comprehensive 12-tier evaluation, advanced orchestration, monitoring, and enterprise capabilities.
Home-page: https://github.com/isathish/agenticaiframework
Author: Sathishkumar Nagarajan
Author-email: mail@sathishkumarnagarajan.com
Classifier: Programming Language :: Python :: 3
Classifier: Programming Language :: Python :: 3.8
Classifier: Programming Language :: Python :: 3.9
Classifier: Programming Language :: Python :: 3.10
Classifier: Programming Language :: Python :: 3.11
Classifier: Programming Language :: Python :: 3.12
Classifier: License :: OSI Approved :: MIT License
Classifier: Operating System :: OS Independent
Requires-Python: >=3.8
License-File: LICENSE
Provides-Extra: docs
Provides-Extra: all
Dynamic: author
Dynamic: author-email
Dynamic: classifier
Dynamic: description
Dynamic: description-content-type
Dynamic: home-page
Dynamic: license-file
Dynamic: provides-extra
Dynamic: requires-python
Dynamic: summary
